paramiko_expect.py
paramiko_expect-0.3.5.dist-info/LICENSE
paramiko_expect-0.3.5.dist-info/METADATA
paramiko_expect-0.3.5.dist-info/WHEEL
paramiko_expect-0.3.5.dist-info/top_level.txt
paramiko_expect-0.3.5.dist-info/RECORD
