Metadata-Version: 2.1
Name: paramiko-expect
Version: 0.3.5
Summary: An expect-like extension for the Paramiko SSH library
Home-page: https://github.com/fgimian/paramiko-expect
Author: Fotis Gimian
Author-email: fgimiansoftware@gmail.com
License: MIT
Platform: Posix
Classifier: Development Status :: 4 - Beta
Classifier: License :: OSI Approved :: MIT License
Classifier: Programming Language :: Python :: 3.4
Classifier: Programming Language :: Python :: 3.5
Classifier: Programming Language :: Python :: 3.6
Classifier: Programming Language :: Python :: 3.7
Classifier: Programming Language :: Python :: 3.8
Classifier: Programming Language :: Python :: 3.9
Classifier: Programming Language :: Python :: Implementation :: PyPy
Classifier: Intended Audience :: Developers
License-File: LICENSE
